asbool/__init__.py
asbool/converter.py
asbool/converter.pyi
asbool/py.typed
asbool-0.2.dist-info/LICENSE
asbool-0.2.dist-info/METADATA
asbool-0.2.dist-info/WHEEL
asbool-0.2.dist-info/top_level.txt
asbool-0.2.dist-info/RECORD
