Metadata-Version: 2.1
Name: asbool
Version: 0.2
Summary: simple converter from ``str`` to ``bool``
Home-page: https://github.com/aodag/asbool
Author: Atsushi Odagiri
Author-email: aodagx@gmail.com
License: MIT,
Platform: UNKNOWN
Classifier: Programming Language :: Python :: 3.6
Classifier: Programming Language :: Python :: 3.7
Classifier: Programming Language :: Python :: 3.8
Classifier: Programming Language :: Python :: 3.9
Requires-Dist: six
Provides-Extra: testing
Requires-Dist: pytest ; extra == 'testing'
Requires-Dist: pytest-cov ; extra == 'testing'
Requires-Dist: pytest-randomly ; extra == 'testing'
